fastvpinns/__init__.py
fastvpinns/FE/FE2D_Cell.py
fastvpinns/FE/__init__.py
fastvpinns/FE/basis_2d_QN_Chebyshev_2.py
fastvpinns/FE/basis_2d_QN_Jacobi.py
fastvpinns/FE/basis_2d_QN_Legendre.py
fastvpinns/FE/basis_2d_QN_Legendre_Special.py
fastvpinns/FE/basis_function_2d.py
fastvpinns/FE/basis_function_3d.py
fastvpinns/FE/fe2d_setup_main.py
fastvpinns/FE/fe_transformation_2d.py
fastvpinns/FE/fe_transformation_3d.py
fastvpinns/FE/fespace.py
fastvpinns/FE/fespace2d.py
fastvpinns/FE/quad_affine.py
fastvpinns/FE/quad_bilinear.py
fastvpinns/FE/quadratureformulas.py
fastvpinns/FE/quadratureformulas_quad2d.py
fastvpinns/Geometry/__init__.py
fastvpinns/Geometry/geometry.py
fastvpinns/Geometry/geometry_2d.py
fastvpinns/data/__init__.py
fastvpinns/data/datahandler.py
fastvpinns/data/datahandler2d.py
fastvpinns/model/__init__.py
fastvpinns/model/model.py
fastvpinns/model/model_hard.py
fastvpinns/model/model_inverse.py
fastvpinns/model/model_inverse_domain.py
fastvpinns/physics/__init__.py
fastvpinns/physics/cd2d.py
fastvpinns/physics/cd2d_inverse.py
fastvpinns/physics/cd2d_inverse_domain.py
fastvpinns/physics/helmholtz2d.py
fastvpinns/physics/poisson2d.py
fastvpinns/physics/poisson2d_inverse.py
fastvpinns/tests/__init__.py
fastvpinns/utils/__init__.py
fastvpinns/utils/compute_utils.py
fastvpinns/utils/plot_utils.py
fastvpinns/utils/print_utils.py
fastvpinns-1.0.2.dist-info/LICENSE
fastvpinns-1.0.2.dist-info/METADATA
fastvpinns-1.0.2.dist-info/WHEEL
fastvpinns-1.0.2.dist-info/top_level.txt
fastvpinns-1.0.2.dist-info/RECORD
