Metadata-Version: 2.1
Name: fastvpinns
Version: 1.0.2
Summary: A fast tensor-driven variational physics-informed neural network library for solving PDEs.
Author-email: Thivin Anandh <thivinanandh@gmail.com>, Divij Ghose <divijghose@gmail.com>, Sashikumaar Ganesan <sashi@iisc.ac.in>
Project-URL: Homepage, https://github.com/cmgcds/fastvpinns
Project-URL: Issues, https://github.com/cmgcds/fastvpinns/issues
Project-URL: Documentation, https://cmgcds.github.io/fastvpinns/
Project-URL: logo, https://raw.githubusercontent.com/cmgcds/fastvpinns/main/Fastvpinns_logo.png
Keywords: PDE,Neural Networks,Physics,AI,Machine Learning,variational PINNs,VPINNs,PINNs,Physics-informed neural networks
Classifier: Development Status :: 4 - Beta
Classifier: Intended Audience :: Developers
Classifier: Intended Audience :: Education
Classifier: Intended Audience :: Science/Research
Classifier: License :: OSI Approved :: MIT License
Classifier: Programming Language :: Python :: 3
Classifier: Programming Language :: Python :: 3 :: Only
Classifier: Programming Language :: Python :: 3.9
Classifier: Programming Language :: Python :: 3.10
Classifier: Programming Language :: Python :: 3.11
Classifier: Programming Language :: Python :: 3.12
Classifier: Topic :: Scientific/Engineering
Classifier: Topic :: Scientific/Engineering :: Artificial Intelligence
Classifier: Topic :: Scientific/Engineering :: Mathematics
Classifier: Topic :: Software Development
Classifier: Topic :: Software Development :: Libraries
Classifier: Topic :: Software Development :: Libraries :: Python Modules
Requires-Python: >=3.8
License-File: LICENSE
Requires-Dist: numpy <=1.23.5,>=1.21
Requires-Dist: pandas <1.4.4
Requires-Dist: matplotlib
Requires-Dist: tensorflow <=2.13.0,>=2.9.1
Requires-Dist: pytest ==8.0.2
Requires-Dist: meshio ==5.3.4
Requires-Dist: pyDOE ==0.3.8
Requires-Dist: tqdm ==4.66.2
Requires-Dist: scipy
Requires-Dist: gmsh ==4.11.0
Requires-Dist: pyyaml
Requires-Dist: rich ==12.5.1
Requires-Dist: black
Requires-Dist: pre-commit
